crinita/__init__.py
crinita/article.py
crinita/config.py
crinita/dataset.py
crinita/entity.py
crinita/entity_detail.py
crinita/entity_list.py
crinita/list_of_articles.py
crinita/list_of_datasets.py
crinita/page.py
crinita/sites.py
crinita/tag.py
crinita/utils.py
crinita/templates/article.jnj
crinita/templates/article_first_preview.jnj
crinita/templates/article_list.jnj
crinita/templates/article_preview.jnj
crinita/templates/dataset.jnj
crinita/templates/dataset_list.jnj
crinita/templates/dataset_preview.jnj
crinita/templates/layout.jnj
crinita/templates/menu.jnj
crinita/templates/recent_entities.jnj
crinita/templates/site_map.jnj
crinita/templates/style.css
crinita/templates/tag_cloud.jnj
crinita/templates/text_in_menu.jnj
crinita-2.0.1.dist-info/LICENSE
crinita-2.0.1.dist-info/METADATA
crinita-2.0.1.dist-info/WHEEL
crinita-2.0.1.dist-info/top_level.txt
crinita-2.0.1.dist-info/RECORD
