Metadata-Version: 2.1
Name: crinita
Version: 2.0.1
Summary: Crinita is a Python application for generating static websites like blogs, data catalogues or simple static pages. It directly creates HTML files based on inputs (without requiring to run any script languages on the server-side).
Home-page: https://crinita.salispace.com
Author: David Salac
Author-email: info@davidsalac.eu
License: UNKNOWN
Platform: UNKNOWN
Classifier: Programming Language :: Python :: 3
Classifier: License :: OSI Approved :: MIT License
Classifier: Operating System :: OS Independent
Requires-Python: >=3.10
License-File: LICENSE
Requires-Dist: Jinja2 (>=2.11.2)
Requires-Dist: classutilities (>=0.2.1)
